runclock/__init__.py
runclock/runclock.py
runclock-1.1.1.dist-info/LICENSE
runclock-1.1.1.dist-info/METADATA
runclock-1.1.1.dist-info/WHEEL
runclock-1.1.1.dist-info/top_level.txt
runclock-1.1.1.dist-info/RECORD
