Metadata-Version: 2.1
Name: runclock
Version: 1.1.1
Summary: With this library you can set time for running your code
Home-page: https://github.com/Ali-Hosseinverdi/run-clock
Author: Ali Hosseinverdi
Author-email: alihv5000@email.com
License: GPLv3
Platform: UNKNOWN
Classifier: License :: OSI Approved :: GNU General Public License v3 (GPLv3)
Classifier: Programming Language :: Python
Classifier: Programming Language :: Python :: 3
Classifier: Programming Language :: Python :: 3.7
Classifier: Programming Language :: Python :: 3.8
Classifier: Programming Language :: Python :: 3.9
Classifier: Programming Language :: Python :: 3.10
License-File: LICENSE
